{
  "products": [
    {
      "id": "2",
      "img": "https://encrypted-tbn0.gstatic.com/images?q=tbn:ANd9GcScEeyYC4Qbk46-F3xcmCTA81zQbYuY5o8hrg&s",
      "title": "shirt",
      "price": 700
    },
    {
      "id": "e6b7",
      "img": "https://encrypted-tbn0.gstatic.com/images?q=tbn:ANd9GcTnjr2UPAL3tCDpeYU-ohk-WKH2o8UXmFUvAA&s",
      "title": "heels",
      "price": "14890"
    },
    {
      "id": "e44a",
      "img": "https://encrypted-tbn0.gstatic.com/images?q=tbn:ANd9GcT090-HwNpxUi85BcaWWYcLy_UivfnoMAp9CA&s",
      "title": "footware",
      "price": "1470"
    }
  ]
}